odoo/addons/stock_picking_deactivate_immediate_transfer/README.rst
odoo/addons/stock_picking_deactivate_immediate_transfer/__init__.py
odoo/addons/stock_picking_deactivate_immediate_transfer/__manifest__.py
odoo/addons/stock_picking_deactivate_immediate_transfer/i18n/stock_picking_deactivate_immediate_transfer.pot
odoo/addons/stock_picking_deactivate_immediate_transfer/readme/CONTRIBUTORS.rst
odoo/addons/stock_picking_deactivate_immediate_transfer/readme/DESCRIPTION.rst
odoo/addons/stock_picking_deactivate_immediate_transfer/readme/USAGE.rst
odoo/addons/stock_picking_deactivate_immediate_transfer/static/description/icon.png
odoo/addons/stock_picking_deactivate_immediate_transfer/static/description/index.html
odoo/addons/stock_picking_deactivate_immediate_transfer/views/stock_picking_views.xml
odoo11_addon_stock_picking_deactivate_immediate_transfer-11.0.1.0.0.99.dev6.dist-info/METADATA
odoo11_addon_stock_picking_deactivate_immediate_transfer-11.0.1.0.0.99.dev6.dist-info/WHEEL
odoo11_addon_stock_picking_deactivate_immediate_transfer-11.0.1.0.0.99.dev6.dist-info/top_level.txt
odoo11_addon_stock_picking_deactivate_immediate_transfer-11.0.1.0.0.99.dev6.dist-info/RECORD
